{
    "type":"origins:multiple",
    "recipe":{
       "type":"origins:recipe",
       "recipe":{
          "id":"origins-classes:thaumaturge_thaumometer",
          "type":"minecraft:crafting_shaped",
          "pattern":[
             " g ",
             "gGg",
             " g "
          ],
          "key":{
             "g":{
                "item":"minecraft:gold_ingot"
             },
             "G":{
                "item":"minecraft:glass_pane"
             }
          },
          "result":{
             "id":"minecraft:clock",
             "count":1
          }
       },
       "condition":{
          "type":"origins:advancement",
          "advancement":"origins-classes:thaumaturge/fundamentals/first_steps"
       }
    },
    "modify_crafting_recipe":{
       "type":"origins:modify_crafting",
       "recipe":"origins-classes:thaumaturge_thaumometer",
       "item_action":{
          "type":"origins:modify",
          "modifier":"origins-classes:thaumaturge/fundamentals/thaumometer"
       },
       "condition":{
          "type":"origins:advancement",
          "advancement":"origins-classes:thaumaturge/fundamentals/first_steps"
       }
    },
    "terra_aspect_detection":{
       "type":"origins:tooltip",
       "item_condition":{
          "type":"origins:ingredient",
          "ingredient":{
             "tag":"origins-classes:thaumaturge/items_with_terra_aspect"
          }
       },
       "text":{
          "type":"translatable",
          "translate":"item.tooltip.thaumometer.terra_aspect",
          "color":"dark_green"
       },
       "order":0,
       "condition":{
          "type":"origins:inventory",
          "inventory_types":[
             "inventory"
          ],
          "process_mode":"items",
          "item_condition":{
             "type":"origins:and",
             "conditions":[
                {
                   "type":"origins:ingredient",
                   "ingredient":{
                      "item":"minecraft:clock"
                   }
                },
                {
                   "type":"origins:custom_data",
                   "nbt":"{thaumaturge:thaumometer}"
                }
             ]
          },
          "comparison":"!=",
          "compare_to":0
       }
    },
    "perditio_aspect_detection":{
        "type":"origins:tooltip",
        "item_condition":{
           "type":"origins:ingredient",
           "ingredient":{
              "tag":"origins-classes:thaumaturge/items_with_perditio_aspect"
           }
        },
        "text":{
           "type":"translatable",
           "translate":"item.tooltip.thaumometer.perditio_aspect",
           "color":"dark_gray"
        },
        "order":0,
        "condition":{
           "type":"origins:inventory",
           "inventory_types":[
              "inventory"
           ],
           "process_mode":"items",
           "item_condition":{
              "type":"origins:and",
              "conditions":[
                 {
                    "type":"origins:ingredient",
                    "ingredient":{
                       "item":"minecraft:clock"
                    }
                 },
                 {
                    "type":"origins:custom_data",
                    "nbt":"{thaumaturge:thaumometer}"
                 }
              ]
           },
           "comparison":"!=",
           "compare_to":0
        }
     }
}